{
    "url": "/api/signup",
    "custom_request": {
        "header": [
            {
                "key": "Content-Type",
                "value": "application/json"
            }
        ],
        "body": {
            "mode": "raw",
            "raw": "{\n  \"title\": \"Mr.\",\n  \"firstName\": \"John\",\n  \"lastName\": \"Adams\",\n  \"genre\": \"Male\"\n}"
        },
        "url": {
            "query": [
                {
                    "key": "email",
                    "value": "john.adams@gmail.com"
                },
                {
                    "key": "password",
                    "value": "mypassword"
                }
            ]
        }
    }
}